[
    {
        "title": "BrazzersExxtra - Pristine Edge And Chloe Surreal",
        "size": "675.09 MB",
        "link": "magnet:?xt=urn:btih:00931261f0b046a7879a6ac3d53d4ffe7958e505&dn=BrazzersExxtra+-+Pristine+Edge+And+Chloe+Surreal+720p+HD+mp4&tr=http%3A%2F%2Ftracker.trackerfix.com%3A80%2Fannounce&tr=udp%3A%2F%2F9.rarbg.me%3A2880&tr=udp%3A%2F%2F9.rarbg.to%3A2970&tr=udp%3A%2F%2Ftracker.slowcheetah.org%3A14760&tr=udp%3A%2F%2Ftracker.fatkhoala.org%3A13710",
        "quality": "720p",
        "se": 109,
        "channel": "brazzers",
        "page": "index"
    },
    {
        "title": "BrazzersExxtra - Armani Black - Blindfold On Ass Up",
        "size": "463.78 MB",
        "link": "magnet:?xt=urn:btih:c7915b4e5495ff648a03cef7071c0c8cc968a07e&dn=BrazzersExxtra+-+Armani+Black+-+Blindfold+On+Ass+Up+720p+HD+mp4&tr=http%3A%2F%2Ftracker.trackerfix.com%3A80%2Fannounce&tr=udp%3A%2F%2F9.rarbg.me%3A2980&tr=udp%3A%2F%2F9.rarbg.to%3A2810&tr=udp%3A%2F%2Ftracker.fatkhoala.org%3A13760&tr=udp%3A%2F%2Ftracker.tallpenguin.org%3A15750",
        "quality": "720p",
        "se": 105,
        "channel": "brazzers",
        "page": "index"
    },
    {
        "title": "BrazzersExxtra - Freya Parker - Dick Stalker",
        "size": "497.21 MB",
        "link": "magnet:?xt=urn:btih:12ca241f43bf81485cc0439fd80f5aa72be3cf2c&dn=BrazzersExxtra+-+Freya+Parker+-+Dick+Stalker+720p+HD+mp4&tr=http%3A%2F%2Ftracker.trackerfix.com%3A80%2Fannounce&tr=udp%3A%2F%2F9.rarbg.me%3A2820&tr=udp%3A%2F%2F9.rarbg.to%3A2810&tr=udp%3A%2F%2Ftracker.fatkhoala.org%3A13720&tr=udp%3A%2F%2Ftracker.tallpenguin.org%3A15720",
        "quality": "720p",
        "se": 98,
        "channel": "brazzers",
        "page": "index"
    },
    {
        "title": "BrazzersExxtra - Whitney Wright And Bella Rolland - She Takes What She Wants",
        "size": "688.41 MB",
        "link": "magnet:?xt=urn:btih:d70c0b9e14d2d68b175e3c7da6627414111f67e0&dn=BrazzersExxtra+-+Whitney+Wright+And+Bella+Rolland+-+She+Takes+What+She+Wants+720p+HD+mp4&tr=http%3A%2F%2Ftracker.trackerfix.com%3A80%2Fannounce&tr=udp%3A%2F%2F9.rarbg.me%3A2790&tr=udp%3A%2F%2F9.rarbg.to%3A2820&tr=udp%3A%2F%2Ftracker.thinelephant.org%3A12760&tr=udp%3A%2F%2Ftracker.slowcheetah.org%3A14770",
        "quality": "720p",
        "se": 92,
        "channel": "brazzers",
        "page": "index"
    },
    {
        "title": "BrazzersExxtra - Rhiannon Ryder - Ring-A-Ding Dick Down",
        "size": "511.54 MB",
        "link": "magnet:?xt=urn:btih:dfd9dc32805a29541804012f2c680c22207665bb&dn=BrazzersExxtra+-+Rhiannon+Ryder+-+Ring-A-Ding+Dick+Down+720p+HD+mp4&tr=http%3A%2F%2Ftracker.trackerfix.com%3A80%2Fannounce&tr=udp%3A%2F%2F9.rarbg.me%3A2750&tr=udp%3A%2F%2F9.rarbg.to%3A2990&tr=udp%3A%2F%2Ftracker.thinelephant.org%3A12730&tr=udp%3A%2F%2Ftracker.slowcheetah.org%3A14710",
        "quality": "720p",
        "se": 52,
        "channel": "brazzers",
        "page": "index"
    },
    {
        "title": "BrazzersExxtra - Cherie Deville - Anatomy Of A Sex Scene MILF Edition",
        "size": "559.71 MB",
        "link": "magnet:?xt=urn:btih:92b8ee609dd7582a0d93e438a14fb4381c4578dc&dn=BrazzersExxtra+-+Cherie+Deville+-+Anatomy+Of+A+Sex+Scene+MILF+Edition+720p+HD+mp4&tr=http%3A%2F%2Ftracker.trackerfix.com%3A80%2Fannounce&tr=udp%3A%2F%2F9.rarbg.me%3A2820&tr=udp%3A%2F%2F9.rarbg.to%3A2810&tr=udp%3A%2F%2Ftracker.slowcheetah.org%3A14730&tr=udp%3A%2F%2Ftracker.tallpenguin.org%3A15740",
        "quality": "720p",
        "se": 71,
        "channel": "brazzers",
        "page": "index"
    },
    {
        "title": "BrazzersExxtra - Lady Lyne - All Natural Access",
        "size": "678.01 MB",
        "link": "magnet:?xt=urn:btih:f5186aca2322f9ca9d8efd56f3e05a75f9d2b939&dn=BrazzersExxtra+-+Lady+Lyne+-+All+Natural+Access+720p+HD+mp4&tr=http%3A%2F%2Ftracker.trackerfix.com%3A80%2Fannounce&tr=udp%3A%2F%2F9.rarbg.me%3A2730&tr=udp%3A%2F%2F9.rarbg.to%3A2950&tr=udp%3A%2F%2Ftracker.fatkhoala.org%3A13760&tr=udp%3A%2F%2Ftracker.slowcheetah.org%3A14740",
        "quality": "720p",
        "se": 65,
        "channel": "brazzers",
        "page": "index"
    },
    {
        "title": "BrazzersExxtra - Nadia White - Wax On Wax All The Way Off",
        "size": "392.40 MB",
        "link": "magnet:?xt=urn:btih:6f7ab6ea6b44dfb3267bfe4641fc6ed783a50811&dn=BrazzersExxtra+-+Nadia+White+-+Wax+On+Wax+All+The+Way+Off+720p+HD+mp4&tr=http%3A%2F%2Ftracker.trackerfix.com%3A80%2Fannounce&tr=udp%3A%2F%2F9.rarbg.me%3A2830&tr=udp%3A%2F%2F9.rarbg.to%3A2850&tr=udp%3A%2F%2Ftracker.thinelephant.org%3A12790&tr=udp%3A%2F%2Ftracker.fatkhoala.org%3A13740",
        "quality": "720p",
        "se": 59,
        "channel": "brazzers",
        "page": "index"
    },
    {
        "title": "BrazzersExxtra - Gianna Dior And Eliza Ibarra",
        "size": "645.38 MB",
        "link": "magnet:?xt=urn:btih:2d8c4ee42606b1a50670b0c200989f1f5a753caf&dn=BrazzersExxtra+-+Gianna+Dior+And+Eliza+Ibarra+720p+HD+mp4&tr=http%3A%2F%2Ftracker.trackerfix.com%3A80%2Fannounce&tr=udp%3A%2F%2F9.rarbg.me%3A2800&tr=udp%3A%2F%2F9.rarbg.to%3A2770&tr=udp%3A%2F%2Ftracker.tallpenguin.org%3A15710&tr=udp%3A%2F%2Ftracker.thinelephant.org%3A12790",
        "quality": "720p",
        "se": 54,
        "channel": "brazzers",
        "page": "index"
    },
    {
        "title": "BrazzersExxtra - Slimthick Vic - Big Tit Vic Chases Older Dick",
        "size": "602.29 MB",
        "link": "magnet:?xt=urn:btih:df4efdb420c9ea1567c9d1fc29ae1c0c0040aeaf&dn=BrazzersExxtra+-+Slimthick+Vic+-+Big+Tit+Vic+Chases+Older+Dick+720p+HD+mp4&tr=http%3A%2F%2Ftracker.trackerfix.com%3A80%2Fannounce&tr=udp%3A%2F%2F9.rarbg.me%3A2850&tr=udp%3A%2F%2F9.rarbg.to%3A2830&tr=udp%3A%2F%2Ftracker.thinelephant.org%3A12730&tr=udp%3A%2F%2Ftracker.slowcheetah.org%3A14740",
        "quality": "720p",
        "se": 32,
        "channel": "brazzers",
        "page": "index"
    },
    {
        "title": "BrazzersExxtra - Syren De Mer - Cum On My Waffles Honey",
        "size": "415.60 MB",
        "link": "magnet:?xt=urn:btih:6de4d85028fd570fbe26ae016f80906a1d82dc26&dn=BrazzersExxtra+-+Syren+De+Mer+-+Cum+On+My+Waffles+Honey+720p+HD+mp4&tr=http%3A%2F%2Ftracker.trackerfix.com%3A80%2Fannounce&tr=udp%3A%2F%2F9.rarbg.me%3A2950&tr=udp%3A%2F%2F9.rarbg.to%3A2850&tr=udp%3A%2F%2Ftracker.thinelephant.org%3A12750&tr=udp%3A%2F%2Ftracker.fatkhoala.org%3A13790",
        "quality": "720p",
        "se": 56,
        "channel": "brazzers",
        "page": "index"
    },
    {
        "title": "BrazzersExxtra - Josephine Jackson - Big Naturals Nurse Gets Kitchen Creeped",
        "size": "511.95 MB",
        "link": "magnet:?xt=urn:btih:b965f2d955763933952efa93c02716eebf21a096&dn=BrazzersExxtra+-+Josephine+Jackson+-+Big+Naturals+Nurse+Gets+Kitchen+Creeped+720p+HD+mp4&tr=http%3A%2F%2Ftracker.trackerfix.com%3A80%2Fannounce&tr=udp%3A%2F%2F9.rarbg.me%3A2730&tr=udp%3A%2F%2F9.rarbg.to%3A2820&tr=udp%3A%2F%2Ftracker.thinelephant.org%3A12720&tr=udp%3A%2F%2Ftracker.tallpenguin.org%3A15800",
        "quality": "720p",
        "se": 96,
        "channel": "brazzers",
        "page": "index"
    },
    {
        "title": "BrazzersExxtra - Katie Morgan And Alexis Fawx",
        "size": "529.75 MB",
        "link": "magnet:?xt=urn:btih:2984d0bc9585bd8930a78be272f9d0dd87d9628d&dn=BrazzersExxtra+-+Katie+Morgan+And+Alexis+Fawx+720p+HD+mp4&tr=http%3A%2F%2Ftracker.trackerfix.com%3A80%2Fannounce&tr=udp%3A%2F%2F9.rarbg.me%3A2900&tr=udp%3A%2F%2F9.rarbg.to%3A2770&tr=udp%3A%2F%2Ftracker.tallpenguin.org%3A15780&tr=udp%3A%2F%2Ftracker.thinelephant.org%3A12750",
        "quality": "720p",
        "se": 49,
        "channel": "brazzers",
        "page": "index"
    },
    {
        "title": "BrazzersExxtra - Simone Richards - Seduced By Simone",
        "size": "502.65 MB",
        "link": "magnet:?xt=urn:btih:0df88f8682abecd28640390432249f1d06a0efcd&dn=BrazzersExxtra+-+Simone+Richards+-+Seduced+By+Simone+720p+HD+mp4&tr=http%3A%2F%2Ftracker.trackerfix.com%3A80%2Fannounce&tr=udp%3A%2F%2F9.rarbg.me%3A2780&tr=udp%3A%2F%2F9.rarbg.to%3A2850&tr=udp%3A%2F%2Ftracker.slowcheetah.org%3A14790&tr=udp%3A%2F%2Ftracker.fatkhoala.org%3A13740",
        "quality": "720p",
        "se": 24,
        "channel": "brazzers",
        "page": "index"
    },
    {
        "title": "BrazzersExxtra - Rachel Starr - Cant You See Im On The Phone",
        "size": "573.92 MB",
        "link": "magnet:?xt=urn:btih:68a3d33c80f192dd6446f301905cfd13e37acf78&dn=BrazzersExxtra+-+Rachel+Starr+-+Cant+You+See+Im+On+The+Phone+720p+HD+mp4&tr=http%3A%2F%2Ftracker.trackerfix.com%3A80%2Fannounce&tr=udp%3A%2F%2F9.rarbg.me%3A2860&tr=udp%3A%2F%2F9.rarbg.to%3A2940&tr=udp%3A%2F%2Ftracker.thinelephant.org%3A12790&tr=udp%3A%2F%2Ftracker.fatkhoala.org%3A13800",
        "quality": "720p",
        "se": 46,
        "channel": "brazzers",
        "page": "index"
    },
    {
        "title": "BrazzersExxtra - Adira Allure And Rebel Rhyder",
        "size": "661.63 MB",
        "link": "magnet:?xt=urn:btih:46964347b81dd1d8ea2ae247c42c823cad45c265&dn=BrazzersExxtra+-+Adira+Allure+And+Rebel+Rhyder+720p+HD+mp4&tr=http%3A%2F%2Ftracker.trackerfix.com%3A80%2Fannounce&tr=udp%3A%2F%2F9.rarbg.me%3A2720&tr=udp%3A%2F%2F9.rarbg.to%3A2980&tr=udp%3A%2F%2Ftracker.slowcheetah.org%3A14760&tr=udp%3A%2F%2Ftracker.tallpenguin.org%3A15710",
        "quality": "720p",
        "se": 37,
        "channel": "brazzers",
        "page": "index"
    },
    {
        "title": "BrazzersExxtra - Kylie Rocket - College Camgirl Fucks The Dean",
        "size": "584.68 MB",
        "link": "magnet:?xt=urn:btih:5cfe4c58e654886bc5aa17b5743782850cefe77e&dn=BrazzersExxtra+-+Kylie+Rocket+-+College+Camgirl+Fucks+The+Dean+720p+HD+mp4&tr=http%3A%2F%2Ftracker.trackerfix.com%3A80%2Fannounce&tr=udp%3A%2F%2F9.rarbg.me%3A2890&tr=udp%3A%2F%2F9.rarbg.to%3A2910&tr=udp%3A%2F%2Ftracker.fatkhoala.org%3A13750&tr=udp%3A%2F%2Ftracker.slowcheetah.org%3A14750",
        "quality": "720p",
        "se": 40,
        "channel": "brazzers",
        "page": "index"
    },
    {
        "title": "BrazzersExxtra - Vanessa Vega - The Never Ending Squirter",
        "size": "398.24 MB",
        "link": "magnet:?xt=urn:btih:a1f798a90a0be69932942a6e57f6e56232d029c7&dn=BrazzersExxtra+-+Vanessa+Vega+-+The+Never+Ending+Squirter+720p+HD+mp4&tr=http%3A%2F%2Ftracker.trackerfix.com%3A80%2Fannounce&tr=udp%3A%2F%2F9.rarbg.me%3A2980&tr=udp%3A%2F%2F9.rarbg.to%3A2750&tr=udp%3A%2F%2Ftracker.tallpenguin.org%3A15740&tr=udp%3A%2F%2Ftracker.thinelephant.org%3A12800",
        "quality": "720p",
        "se": 41,
        "channel": "brazzers",
        "page": "index"
    },
    {
        "title": "BrazzersExxtra - Codi Vore, Jazmin Luv And Kate Dee - Lets Party",
        "size": "620.60 MB",
        "link": "magnet:?xt=urn:btih:a2eaa508857848c11a6d464b57a4472aa0ae9691&dn=BrazzersExxtra+-+Codi+Vore%2C+Jazmin+Luv+And+Kate+Dee+-+Lets+Party+720p+HD+mp4&tr=http%3A%2F%2Ftracker.trackerfix.com%3A80%2Fannounce&tr=udp%3A%2F%2F9.rarbg.me%3A2800&tr=udp%3A%2F%2F9.rarbg.to%3A2940&tr=udp%3A%2F%2Ftracker.tallpenguin.org%3A15740&tr=udp%3A%2F%2Ftracker.thinelephant.org%3A12740",
        "quality": "720p",
        "se": 39,
        "channel": "brazzers",
        "page": "index"
    },
    {
        "title": "BrazzersExxtra - Payton Hall - Gilf Makes His Cock Cozy",
        "size": "418.13 MB",
        "link": "magnet:?xt=urn:btih:f4f609fb0d8e05b5302b615dcac432b246d95c60&dn=BrazzersExxtra+-+Payton+Hall+-+Gilf+Makes+His+Cock+Cozy+720p+HD+mp4&tr=http%3A%2F%2Ftracker.trackerfix.com%3A80%2Fannounce&tr=udp%3A%2F%2F9.rarbg.me%3A2770&tr=udp%3A%2F%2F9.rarbg.to%3A2870&tr=udp%3A%2F%2Ftracker.fatkhoala.org%3A13730&tr=udp%3A%2F%2Ftracker.slowcheetah.org%3A14780",
        "quality": "720p",
        "se": 19,
        "channel": "brazzers",
        "page": "index"
    },
    {
        "title": "BrazzersExxtra - Alexis Fawx - The Bidding War",
        "size": "744.15 MB",
        "link": "magnet:?xt=urn:btih:4aa2c6b86ca4e7c8819e165d0f919d2d4c8d88c1&dn=BrazzersExxtra+-+Alexis+Fawx+-+The+Bidding+War+720p+HD+mp4&tr=http%3A%2F%2Ftracker.trackerfix.com%3A80%2Fannounce&tr=udp%3A%2F%2F9.rarbg.me%3A2860&tr=udp%3A%2F%2F9.rarbg.to%3A2850&tr=udp%3A%2F%2Ftracker.slowcheetah.org%3A14780&tr=udp%3A%2F%2Ftracker.tallpenguin.org%3A15740",
        "quality": "720p",
        "se": 50,
        "channel": "brazzers",
        "page": "index"
    },
    {
        "title": "BrazzersExxtra - Lulu Chu - Lulus Lair Of Lust",
        "size": "513.66 MB",
        "link": "magnet:?xt=urn:btih:49a4322a0ff0af1bc249a0768aac6f60a8d228ce&dn=BrazzersExxtra+-+Lulu+Chu+-+Lulus+Lair+Of+Lust+720p+HD+mp4&tr=http%3A%2F%2Ftracker.trackerfix.com%3A80%2Fannounce&tr=udp%3A%2F%2F9.rarbg.me%3A2980&tr=udp%3A%2F%2F9.rarbg.to%3A2880&tr=udp%3A%2F%2Ftracker.slowcheetah.org%3A14780&tr=udp%3A%2F%2Ftracker.tallpenguin.org%3A15800",
        "quality": "720p",
        "se": 29,
        "channel": "brazzers",
        "page": "index"
    },
    {
        "title": "BrazzersExxtra - Vanna Bardot And Lily Lou - Grandpas 3way Getaway Part 2",
        "size": "616.74 MB",
        "link": "magnet:?xt=urn:btih:5f937d159b3a198159f7a96438443fe14d24da62&dn=BrazzersExxtra+-+Vanna+Bardot+And+Lily+Lou+-+Grandpas+3way+Getaway+Part+2+720p+HD+mp4&tr=http%3A%2F%2Ftracker.trackerfix.com%3A80%2Fannounce&tr=udp%3A%2F%2F9.rarbg.me%3A2890&tr=udp%3A%2F%2F9.rarbg.to%3A2770&tr=udp%3A%2F%2Ftracker.fatkhoala.org%3A13790&tr=udp%3A%2F%2Ftracker.slowcheetah.org%3A14760",
        "quality": "720p",
        "se": 32,
        "channel": "brazzers",
        "page": "index"
    },
    {
        "title": "BrazzersExxtra - Vanna Bardot And Lily Lou - Grandpas 3way Getaway Part 1",
        "size": "754.94 MB",
        "link": "magnet:?xt=urn:btih:6e06b0e83797fc30f13df58908e14234a7792c97&dn=BrazzersExxtra+-+Vanna+Bardot+And+Lily+Lou+-+Grandpas+3way+Getaway+Part+1+720p+HD+mp4&tr=http%3A%2F%2Ftracker.trackerfix.com%3A80%2Fannounce&tr=udp%3A%2F%2F9.rarbg.me%3A2960&tr=udp%3A%2F%2F9.rarbg.to%3A2720&tr=udp%3A%2F%2Ftracker.thinelephant.org%3A12720&tr=udp%3A%2F%2Ftracker.fatkhoala.org%3A13730",
        "quality": "720p",
        "se": 32,
        "channel": "brazzers",
        "page": "index"
    },
    {
        "title": "BrazzersExxtra - Mocha Menage And Armani Black - Double-Booked Dicking",
        "size": "538.78 MB",
        "link": "magnet:?xt=urn:btih:cf61cdf56dd996f5b1fb106dc3be4d39855f2a32&dn=BrazzersExxtra+-+Mocha+Menage+And+Armani+Black+-+Double-Booked+Dicking+720p+HD+mp4&tr=http%3A%2F%2Ftracker.trackerfix.com%3A80%2Fannounce&tr=udp%3A%2F%2F9.rarbg.me%3A2860&tr=udp%3A%2F%2F9.rarbg.to%3A2870&tr=udp%3A%2F%2Ftracker.fatkhoala.org%3A13770&tr=udp%3A%2F%2Ftracker.tallpenguin.org%3A15800",
        "quality": "720p",
        "se": 18,
        "channel": "brazzers",
        "page": "index"
    },
    {
        "title": "BrazzersExxtra - Kay Carter And Delilah Day - My GFs Big Sister Does Anal",
        "size": "563.38 MB",
        "link": "magnet:?xt=urn:btih:571f681cc9c73f7542b8b3f86cc2307dc44630c3&dn=BrazzersExxtra+-+Kay+Carter+And+Delilah+Day+-+My+GFs+Big+Sister+Does+Anal+720p+HD+mp4&tr=http%3A%2F%2Ftracker.trackerfix.com%3A80%2Fannounce&tr=udp%3A%2F%2F9.rarbg.me%3A2830&tr=udp%3A%2F%2F9.rarbg.to%3A2770&tr=udp%3A%2F%2Ftracker.fatkhoala.org%3A13800&tr=udp%3A%2F%2Ftracker.slowcheetah.org%3A14730",
        "quality": "720p",
        "se": 50,
        "channel": "brazzers",
        "page": "index"
    },
    {
        "title": "BrazzersExxtra - Khloe Kapri And Carmela Clutch - Caught And Kinky",
        "size": "518.41 MB",
        "link": "magnet:?xt=urn:btih:cb614eab90e40fe229991554f76152b0ef5f5cee&dn=BrazzersExxtra+-+Khloe+Kapri+And+Carmela+Clutch+-+Caught+And+Kinky+720p+HD+mp4&tr=http%3A%2F%2Ftracker.trackerfix.com%3A80%2Fannounce&tr=udp%3A%2F%2F9.rarbg.me%3A2830&tr=udp%3A%2F%2F9.rarbg.to%3A2800&tr=udp%3A%2F%2Ftracker.fatkhoala.org%3A13780&tr=udp%3A%2F%2Ftracker.tallpenguin.org%3A15730",
        "quality": "720p",
        "se": 24,
        "channel": "brazzers",
        "page": "index"
    },
    {
        "title": "BrazzersExxtra - Ashley Lane - Public Sucking Feature Presentation",
        "size": "497.90 MB",
        "link": "magnet:?xt=urn:btih:1e5e9699fd81b5c12807eb2188e1751149c65af4&dn=BrazzersExxtra+-+Ashley+Lane+-+Public+Sucking+Feature+Presentation+720p+HD+mp4&tr=http%3A%2F%2Ftracker.trackerfix.com%3A80%2Fannounce&tr=udp%3A%2F%2F9.rarbg.me%3A2930&tr=udp%3A%2F%2F9.rarbg.to%3A2880&tr=udp%3A%2F%2Ftracker.fatkhoala.org%3A13730&tr=udp%3A%2F%2Ftracker.tallpenguin.org%3A15790",
        "quality": "720p",
        "se": 20,
        "channel": "brazzers",
        "page": "index"
    },
    {
        "title": "BrazzersExxtra - Rose Jones - Personal Sex Assistant",
        "size": "586.76 MB",
        "link": "magnet:?xt=urn:btih:9f0ee91c96b1b71b80b12a40d401ddcda2ebe33c&dn=BrazzersExxtra+-+Rose+Jones+-+Personal+Sex+Assistant+720p+HD+mp4&tr=http%3A%2F%2Ftracker.trackerfix.com%3A80%2Fannounce&tr=udp%3A%2F%2F9.rarbg.me%3A2900&tr=udp%3A%2F%2F9.rarbg.to%3A2940&tr=udp%3A%2F%2Ftracker.slowcheetah.org%3A14780&tr=udp%3A%2F%2Ftracker.tallpenguin.org%3A15720",
        "quality": "720p",
        "se": 28,
        "channel": "brazzers",
        "page": "index"
    },
    {
        "title": "BrazzersExxtra - Sofia Lee And Ebony Mystique - Auctioning Her Ass",
        "size": "667.21 MB",
        "link": "magnet:?xt=urn:btih:ebc2bd1569f03eb85263dd772381a416d2f5a2e9&dn=BrazzersExxtra+-+Sofia+Lee+And+Ebony+Mystique+-+Auctioning+Her+Ass+720p+HD+mp4&tr=http%3A%2F%2Ftracker.trackerfix.com%3A80%2Fannounce&tr=udp%3A%2F%2F9.rarbg.me%3A2990&tr=udp%3A%2F%2F9.rarbg.to%3A2860&tr=udp%3A%2F%2Ftracker.fatkhoala.org%3A13710&tr=udp%3A%2F%2Ftracker.thinelephant.org%3A12780",
        "quality": "720p",
        "se": 28,
        "channel": "brazzers",
        "page": "index"
    },
    {
        "title": "BrazzersExxtra - Angela White - A To ZZ",
        "size": "433.30 MB",
        "link": "magnet:?xt=urn:btih:e7cd36d62f1a1f053e6d165354b94e2482bc948e&dn=BrazzersExxtra+-+Angela+White+-+A+To+ZZ+720p+HD+mp4&tr=http%3A%2F%2Ftracker.trackerfix.com%3A80%2Fannounce&tr=udp%3A%2F%2F9.rarbg.me%3A2900&tr=udp%3A%2F%2F9.rarbg.to%3A2810&tr=udp%3A%2F%2Ftracker.fatkhoala.org%3A13780&tr=udp%3A%2F%2Ftracker.thinelephant.org%3A12780",
        "quality": "720p",
        "se": 40,
        "channel": "brazzers",
        "page": "index"
    },
    {
        "title": "BrazzersExxtra - Tina Fire And Irina Cage - Workplace Pussy Party",
        "size": "662.00 MB",
        "link": "magnet:?xt=urn:btih:e26bd258c6578abfb89f27c12423d1e9073699a4&dn=BrazzersExxtra+-+Tina+Fire+And+Irina+Cage+-+Workplace+Pussy+Party+720p+HD+mp4&tr=http%3A%2F%2Ftracker.trackerfix.com%3A80%2Fannounce&tr=udp%3A%2F%2F9.rarbg.me%3A2840&tr=udp%3A%2F%2F9.rarbg.to%3A2860&tr=udp%3A%2F%2Ftracker.fatkhoala.org%3A13760&tr=udp%3A%2F%2Ftracker.thinelephant.org%3A12720",
        "quality": "720p",
        "se": 17,
        "channel": "brazzers",
        "page": "index"
    },
    {
        "title": "BrazzersExxtra - Katie Morgan And Gia Derza - Blast-Sisted Living Threeway",
        "size": "449.57 MB",
        "link": "magnet:?xt=urn:btih:6cb7b1102cf109126da152b6823c2127cedae0b3&dn=BrazzersExxtra+-+Katie+Morgan+And+Gia+Derza+-+Blast-Sisted+Living+Threeway+720p+HD+mp4&tr=http%3A%2F%2Ftracker.trackerfix.com%3A80%2Fannounce&tr=udp%3A%2F%2F9.rarbg.me%3A2900&tr=udp%3A%2F%2F9.rarbg.to%3A2960&tr=udp%3A%2F%2Ftracker.thinelephant.org%3A12760&tr=udp%3A%2F%2Ftracker.fatkhoala.org%3A13770",
        "quality": "720p",
        "se": 24,
        "channel": "brazzers",
        "page": "index"
    },
    {
        "title": "BrazzersExxtra - Savannah Bond - Guide To Anal Twerking",
        "size": "409.11 MB",
        "link": "magnet:?xt=urn:btih:15659500568ed781c05b21d5bd2cb02f29b4e033&dn=BrazzersExxtra+-+Savannah+Bond+-+Guide+To+Anal+Twerking+720p+HD+mp4&tr=http%3A%2F%2Ftracker.trackerfix.com%3A80%2Fannounce&tr=udp%3A%2F%2F9.rarbg.me%3A2940&tr=udp%3A%2F%2F9.rarbg.to%3A2950&tr=udp%3A%2F%2Ftracker.fatkhoala.org%3A13770&tr=udp%3A%2F%2Ftracker.tallpenguin.org%3A15800",
        "quality": "720p",
        "se": 34,
        "channel": "brazzers",
        "page": "index"
    },
    {
        "title": "BrazzersExxtra - Skye Blue - Ripped And Torn",
        "size": "457.97 MB",
        "link": "magnet:?xt=urn:btih:06b8c396f54152ceacc5a09243c4b2f69f80e8d8&dn=BrazzersExxtra+-+Skye+Blue+-+Ripped+And+Torn+720p+HD+mp4&tr=http%3A%2F%2Ftracker.trackerfix.com%3A80%2Fannounce&tr=udp%3A%2F%2F9.rarbg.me%3A2830&tr=udp%3A%2F%2F9.rarbg.to%3A2860&tr=udp%3A%2F%2Ftracker.slowcheetah.org%3A14750&tr=udp%3A%2F%2Ftracker.fatkhoala.org%3A13730",
        "quality": "720p",
        "se": 21,
        "channel": "brazzers",
        "page": "index"
    },
    {
        "title": "BrazzersExxtra - Andi James And Bess Breast - Pervy Mom Fucks My Boyfriend",
        "size": "359.28 MB",
        "link": "magnet:?xt=urn:btih:9134c7e17a2b390d294bb014b632baf238caad99&dn=BrazzersExxtra+-+Andi+James+And+Bess+Breast+-+Pervy+Mom+Fucks+My+Boyfriend+720p+HD+mp4&tr=http%3A%2F%2Ftracker.trackerfix.com%3A80%2Fannounce&tr=udp%3A%2F%2F9.rarbg.me%3A2900&tr=udp%3A%2F%2F9.rarbg.to%3A2970&tr=udp%3A%2F%2Ftracker.slowcheetah.org%3A14770&tr=udp%3A%2F%2Ftracker.tallpenguin.org%3A15740",
        "quality": "720p",
        "se": 37,
        "channel": "brazzers",
        "page": "index"
    },
    {
        "title": "BrazzersExxtra - Sky Pierce - Breakfast Sex With Extra Oil",
        "size": "482.57 MB",
        "link": "magnet:?xt=urn:btih:52bb51293092b348996ed2b0db027fac858045ac&dn=BrazzersExxtra+-+Sky+Pierce+-+Breakfast+Sex+With+Extra+Oil+720p+HD+mp4&tr=http%3A%2F%2Ftracker.trackerfix.com%3A80%2Fannounce&tr=udp%3A%2F%2F9.rarbg.me%3A2860&tr=udp%3A%2F%2F9.rarbg.to%3A2970&tr=udp%3A%2F%2Ftracker.fatkhoala.org%3A13730&tr=udp%3A%2F%2Ftracker.slowcheetah.org%3A14730",
        "quality": "720p",
        "se": 17,
        "channel": "brazzers",
        "page": "index"
    },
    {
        "title": "BrazzersExxtra - Bunny Madison - Work Him Out",
        "size": "429.70 MB",
        "link": "magnet:?xt=urn:btih:245496189b62c95efcb8b86bce3573770da534fb&dn=BrazzersExxtra+-+Bunny+Madison+-+Work+Him+Out+720p+HD+mp4&tr=http%3A%2F%2Ftracker.trackerfix.com%3A80%2Fannounce&tr=udp%3A%2F%2F9.rarbg.me%3A2880&tr=udp%3A%2F%2F9.rarbg.to%3A2870&tr=udp%3A%2F%2Ftracker.tallpenguin.org%3A15790&tr=udp%3A%2F%2Ftracker.thinelephant.org%3A12780",
        "quality": "720p",
        "se": 27,
        "channel": "brazzers",
        "page": "index"
    },
    {
        "title": "BrazzersExxtra - Barbie Crystal And Imani - Seduction The Wrong Night",
        "size": "587.72 MB",
        "link": "magnet:?xt=urn:btih:6cf50b0184e08ec87d4cb6703a0b5af90cce46b9&dn=BrazzersExxtra+-+Barbie+Crystal+And+Imani+-+Seduction+The+Wrong+Night+720p+HD+mp4&tr=http%3A%2F%2Ftracker.trackerfix.com%3A80%2Fannounce&tr=udp%3A%2F%2F9.rarbg.me%3A2730&tr=udp%3A%2F%2F9.rarbg.to%3A2750&tr=udp%3A%2F%2Ftracker.thinelephant.org%3A12710&tr=udp%3A%2F%2Ftracker.fatkhoala.org%3A13760",
        "quality": "720p",
        "se": 11,
        "channel": "brazzers",
        "page": "index"
    },
    {
        "title": "BrazzersExxtra - Vicki Chase - Vicki Gets A Lesson In Anal",
        "size": "366.16 MB",
        "link": "magnet:?xt=urn:btih:30d50edd8f4666cf8ac91abd0c327d3b093946f3&dn=BrazzersExxtra+-+Vicki+Chase+-+Vicki+Gets+A+Lesson+In+Anal+720p+HD+mp4&tr=http%3A%2F%2Ftracker.trackerfix.com%3A80%2Fannounce&tr=udp%3A%2F%2F9.rarbg.me%3A2850&tr=udp%3A%2F%2F9.rarbg.to%3A2890&tr=udp%3A%2F%2Ftracker.tallpenguin.org%3A15780&tr=udp%3A%2F%2Ftracker.slowcheetah.org%3A14710",
        "quality": "720p",
        "se": 28,
        "channel": "brazzers",
        "page": "index"
    },
    {
        "title": "BrazzersExxtra - Kimora Quin - Fuck Me On Company Time",
        "size": "559.93 MB",
        "link": "magnet:?xt=urn:btih:6c8bd79e043e89048210cb88987520acff9394fa&dn=BrazzersExxtra+-+Kimora+Quin+-+Fuck+Me+On+Company+Time+720p+HD+mp4&tr=http%3A%2F%2Ftracker.trackerfix.com%3A80%2Fannounce&tr=udp%3A%2F%2F9.rarbg.me%3A2800&tr=udp%3A%2F%2F9.rarbg.to%3A2730&tr=udp%3A%2F%2Ftracker.thinelephant.org%3A12780&tr=udp%3A%2F%2Ftracker.fatkhoala.org%3A13760",
        "quality": "720p",
        "se": 14,
        "channel": "brazzers",
        "page": "index"
    },
    {
        "title": "BrazzersExxtra - Syren De Mer And Jesse Pony",
        "size": "381.48 MB",
        "link": "magnet:?xt=urn:btih:45a3442e2ff69a196d77ebee3e9d9c576f85bc6c&dn=BrazzersExxtra+-+Syren+De+Mer+And+Jesse+Pony+720p+HD+mp4&tr=http%3A%2F%2Ftracker.trackerfix.com%3A80%2Fannounce&tr=udp%3A%2F%2F9.rarbg.me%3A2890&tr=udp%3A%2F%2F9.rarbg.to%3A2880&tr=udp%3A%2F%2Ftracker.slowcheetah.org%3A14710&tr=udp%3A%2F%2Ftracker.tallpenguin.org%3A15760",
        "quality": "720p",
        "se": 31,
        "channel": "brazzers",
        "page": "index"
    },
    {
        "title": "BrazzersExxtra - Venus Afrodita - Invading Venus",
        "size": "522.14 MB",
        "link": "magnet:?xt=urn:btih:cb9d38b6828ecf1bbbd5bed1dcc6ff7fb2a0a349&dn=BrazzersExxtra+-+Venus+Afrodita+-+Invading+Venus+720p+HD+mp4&tr=http%3A%2F%2Ftracker.trackerfix.com%3A80%2Fannounce&tr=udp%3A%2F%2F9.rarbg.me%3A2760&tr=udp%3A%2F%2F9.rarbg.to%3A2990&tr=udp%3A%2F%2Ftracker.fatkhoala.org%3A13720&tr=udp%3A%2F%2Ftracker.tallpenguin.org%3A15720",
        "quality": "720p",
        "se": 10,
        "channel": "brazzers",
        "page": "index"
    },
    {
        "title": "BrazzersExxtra - LaSirena69 And Hazel Grace - Jet Set Jizzers",
        "size": "350.34 MB",
        "link": "magnet:?xt=urn:btih:3e138cf4ba86575d4c27be7f41043c0334c2a191&dn=BrazzersExxtra+-+LaSirena69+And+Hazel+Grace+-+Jet+Set+Jizzers+720p+HD+mp4&tr=http%3A%2F%2Ftracker.trackerfix.com%3A80%2Fannounce&tr=udp%3A%2F%2F9.rarbg.me%3A2760&tr=udp%3A%2F%2F9.rarbg.to%3A2970&tr=udp%3A%2F%2Ftracker.tallpenguin.org%3A15790&tr=udp%3A%2F%2Ftracker.slowcheetah.org%3A14760",
        "quality": "720p",
        "se": 54,
        "channel": "brazzers",
        "page": "index"
    },
    {
        "title": "BrazzersExxtra - Marica Hase And Lulu Chu - Measuring Up",
        "size": "816.17 MB",
        "link": "magnet:?xt=urn:btih:28653e12ab13f8d553e1f35c827d4f1776d3e5d2&dn=BrazzersExxtra+-+Marica+Hase+And+Lulu+Chu+-+Measuring+Up+720p+HD+mp4&tr=http%3A%2F%2Ftracker.trackerfix.com%3A80%2Fannounce&tr=udp%3A%2F%2F9.rarbg.me%3A2860&tr=udp%3A%2F%2F9.rarbg.to%3A2870&tr=udp%3A%2F%2Ftracker.tallpenguin.org%3A15730&tr=udp%3A%2F%2Ftracker.thinelephant.org%3A12750",
        "quality": "720p",
        "se": 19,
        "channel": "brazzers",
        "page": "index"
    },
    {
        "title": "BrazzersExxtra - Cherie Deville - I Ordered A Cheriedroid",
        "size": "535.53 MB",
        "link": "magnet:?xt=urn:btih:9d67395f74f9281f893fbe64fe1c51a9e0e75dda&dn=BrazzersExxtra+-+Cherie+Deville+-+I+Ordered+A+Cheriedroid+720p+HD+mp4&tr=http%3A%2F%2Ftracker.trackerfix.com%3A80%2Fannounce&tr=udp%3A%2F%2F9.rarbg.me%3A2760&tr=udp%3A%2F%2F9.rarbg.to%3A2880&tr=udp%3A%2F%2Ftracker.slowcheetah.org%3A14780&tr=udp%3A%2F%2Ftracker.tallpenguin.org%3A15720",
        "quality": "720p",
        "se": 20,
        "channel": "brazzers",
        "page": "index"
    },
    {
        "title": "BrazzersExxtra - Rae Lil Black - Brother Bangs The Bride-To-Be",
        "size": "506.58 MB",
        "link": "magnet:?xt=urn:btih:2fbf4b5d1a32700859519b9a37983908a80dc885&dn=BrazzersExxtra+-+Rae+Lil+Black+-+Brother+Bangs+The+Bride-To-Be+720p+HD+mp4&tr=http%3A%2F%2Ftracker.trackerfix.com%3A80%2Fannounce&tr=udp%3A%2F%2F9.rarbg.me%3A2810&tr=udp%3A%2F%2F9.rarbg.to%3A2900&tr=udp%3A%2F%2Ftracker.tallpenguin.org%3A15800&tr=udp%3A%2F%2Ftracker.thinelephant.org%3A12750",
        "quality": "720p",
        "se": 73,
        "channel": "brazzers",
        "page": "index"
    },
    {
        "title": "BrazzersExxtra - Luna Star - Teasing Two For Luna",
        "size": "396.32 MB",
        "link": "magnet:?xt=urn:btih:feb84eb476f5d13252856c8f133cb8b9815df168&dn=BrazzersExxtra+-+Luna+Star+-+Teasing+Two+For+Luna+720p+HD+mp4&tr=http%3A%2F%2Ftracker.trackerfix.com%3A80%2Fannounce&tr=udp%3A%2F%2F9.rarbg.me%3A2990&tr=udp%3A%2F%2F9.rarbg.to%3A2850&tr=udp%3A%2F%2Ftracker.fatkhoala.org%3A13740&tr=udp%3A%2F%2Ftracker.slowcheetah.org%3A14770",
        "quality": "720p",
        "se": 22,
        "channel": "brazzers",
        "page": "index"
    },
    {
        "title": "BrazzersExxtra - Lana Rose - Top Model",
        "size": "612.06 MB",
        "link": "magnet:?xt=urn:btih:6e86d6d95cfc4f73ca400ba5c8db55b6d7f32533&dn=BrazzersExxtra+-+Lana+Rose+-+Top+Model+720p+HD+mp4&tr=http%3A%2F%2Ftracker.trackerfix.com%3A80%2Fannounce&tr=udp%3A%2F%2F9.rarbg.me%3A2760&tr=udp%3A%2F%2F9.rarbg.to%3A2970&tr=udp%3A%2F%2Ftracker.thinelephant.org%3A12760&tr=udp%3A%2F%2Ftracker.fatkhoala.org%3A13780",
        "quality": "720p",
        "se": 11,
        "channel": "brazzers",
        "page": "index"
    },
    {
        "title": "BrazzersExxtra - Kira Noir - Testing The Sheets",
        "size": "433.65 MB",
        "link": "magnet:?xt=urn:btih:3035061da4c3eb004fad7cc39285933df00c9b54&dn=BrazzersExxtra+-+Kira+Noir+-+Testing+The+Sheets+720p+HD+mp4&tr=http%3A%2F%2Ftracker.trackerfix.com%3A80%2Fannounce&tr=udp%3A%2F%2F9.rarbg.me%3A2780&tr=udp%3A%2F%2F9.rarbg.to%3A2980&tr=udp%3A%2F%2Ftracker.tallpenguin.org%3A15770&tr=udp%3A%2F%2Ftracker.slowcheetah.org%3A14750",
        "quality": "720p",
        "se": 17,
        "channel": "brazzers",
        "page": "index"
    }
]